paygo_utils/___init__.py
paygo_utils/constants.py
paygo_utils/dateutils.py
paygo_utils/exceptions.py
paygo_utils/money.py
paygo_utils/utilities.py
paygo_utils-0.0.18.dist-info/LICENSE.txt
paygo_utils-0.0.18.dist-info/METADATA
paygo_utils-0.0.18.dist-info/WHEEL
paygo_utils-0.0.18.dist-info/top_level.txt
paygo_utils-0.0.18.dist-info/RECORD
