Metadata-Version: 2.1
Name: paygo-utils
Version: 0.0.18
Summary: This is a utilities library that contains the base files needed by every microservice
Home-page: UNKNOWN
Author: Umar Kayondo
Author-email: umabravo70@gmail.com
License: MIT
Keywords: paygo utils
Platform: UNKNOWN
Classifier: Development Status :: 5 - Production/Stable
Classifier: Intended Audience :: Developers
Classifier: Operating System :: Microsoft :: Windows :: Windows 10
Classifier: License :: OSI Approved :: MIT License
Classifier: Programming Language :: Python :: 3
